[
  {
    "name": "guardar_nombre",
    "module": "memory",
    "priority": 1,
    "regex": [
      "^mi nombre es (.+)$",
      "^me llamo (.+)$",
      "^puedes llamarme (.+)$"
    ],
    "command": "remember",
    "key": "nombre"
  },
  {
    "name": "recordar_nombre",
    "module": "memory",
    "priority": 2,
    "regex": [
      "^como me llamo$",
      "^cómo me llamo$",
      "^¿como me llamo\\??$",
      "^¿cómo me llamo\\??$",
      "^quien soy$",
      "^quién soy$",
      "^cual es mi nombre$",
      "^cuál es mi nombre$",
      "^¿cual es mi nombre\\??$",
      "^¿cuál es mi nombre\\??$"
    ],
    "command": "recall",
    "key": "nombre"
  },
  {
    "name": "guardar_edad",
    "module": "memory",
    "priority": 1,
    "regex": [
        "^tengo (\\d+) anos$",
        "^tengo (\\d+)$"
    ],
    "command": "remember",
    "key": "edad"
  },
    {
    "name": "recordar_edad",
    "module": "memory",
    "priority": 2,
    "regex": [
        "^que edad tengo$",
        "^cuantos anos tengo$",
        "^mi edad$"
    ],
    "command": "recall",
    "key": "edad"
},
  {
    "name": "guardar_ciudad",
    "module": "memory",
    "priority": 1,
    "regex": [
      "^vivo en (.+)$"
    ],
    "command": "remember",
    "key": "ciudad"
  },
  {
    "name": "recordar_ciudad",
    "module": "memory",
    "priority": 2,
    "regex": [
      "^donde vivo$",
      "^dónde vivo$",
      "^¿donde vivo\\??$",
      "^¿dónde vivo\\??$"
    ],
    "command": "recall",
    "key": "ciudad"
  },
  {
    "name": "guardar_profesion",
    "module": "memory",
    "priority": 1,
    "regex": [
      "^soy (.+)$",
      "^trabajo como (.+)$"
    ],
    "command": "remember",
    "key": "profesion"
  },
  {
    "name": "recordar_profesion",
    "module": "memory",
    "priority": 2,
    "regex": [
      "^que soy$",
      "^qué soy$",
      "^¿que soy\\??$",
      "^¿qué soy\\??$",
      "^cual es mi profesion$",
      "^cuál es mi profesión$",
      "^¿cual es mi profesion\\??$",
      "^¿cuál es mi profesión\\??$"
    ],
    "command": "recall",
    "key": "profesion"
  },
  {
    "name": "buscar_conocimiento",
    "module": "knowledge",
    "priority": 5,
    "regex": [
      "^que es (.+)$",
      "^quien es (.+)$",
      "^qué es (.+)$",
      "^quién es (.+)$",
      "^definicion de (.+)$",
      "^definición de (.+)$",
      "^explicame (.+)$",
      "^explícame (.+)$",
      "^hablame de (.+)$",
      "^háblame de (.+)$"
    ],
    "command": "search",
    "topic_group": 1
  },
  {
    "name": "buscar_web",
    "module": "web",
    "priority": 20,
    "regex": [
      "^busca (.+)$",
      "^buscar (.+)$",
      "^investiga (.+)$",
      "^consulta (.+)$",
      "^busca en internet (.+)$",
      "^investiga en internet (.+)$"
    ],
    "command": "search",
    "topic_group": 1
  },
  {
  "name": "crear_documento",
  "module": "document",
  "priority": 15,
  "regex": [
    "^crea un documento ([a-zA-Z0-9_-]+) con el texto (.+)$",
    "^crear documento ([a-zA-Z0-9_-]+) con el texto (.+)$",
    "^nuevo documento ([a-zA-Z0-9_-]+) con el texto (.+)$",
    "^genera un documento ([a-zA-Z0-9_-]+) con el texto (.+)$"
  ],
  "command": "create",
  "topic_group": 1,
  "content_group": 2
},
{
  "name": "crear_documento_formato",
  "module": "document",
  "priority": 15,
  "regex": [
    "^crea un ([a-z]+) ([a-zA-Z0-9_-]+)(?: con el texto (.*))?$",
    "^genera un ([a-z]+) ([a-zA-Z0-9_-]+)(?: con el texto (.*))?$",
    "^nuevo ([a-z]+) ([a-zA-Z0-9_-]+)(?: con el texto (.*))?$"
  ],
  "command": "create",
  "format_group": 1,
  "topic_group": 2,
  "content_group": 3
},
  {
    "name": "abrir_app",
    "module": "system",
    "priority": 10,
    "regex": [
        "^abre (.+)$",
        "^abrir (.+)$",
        "^ejecuta (.+)$",
        "^inicia (.+)$",
        "^abre la aplicacion (.+)$",
        "^abre el programa (.+)$"
    ],
    "command": "open",
    "topic_group": 1
},
  
  {
    "name": "cerrar_app",
    "module": "system",
    "priority": 10,
    "regex": [
      "^cierra (.+)$",
      "^termina (.+)$",
      "^finaliza (.+)$"
    ],
    "command": "close",
    "topic_group": 1
  },
  {
    "name": "calcular",
    "module": "calculator",
    "priority": 8,
    "regex": [
      "^cuanto es (.+)$",
      "^calcula (.+)$",
      "^resolver (.+)$"
    ],
    "command": "calculate",
    "topic_group": 1
  },
  {
    "name": "hora",
    "module": "system",
    "priority": 8,
    "regex": [
      "^que hora es$",
      "^qué hora es$"
    ],
    "command": "time"
  },
  {
    "name": "fecha",
    "module": "system",
    "priority": 8,
    "regex": [
      "^que fecha es hoy$",
      "^qué fecha es hoy$",
      "^fecha de hoy$"
    ],
    "command": "date"
  },
  {
    "name": "clima",
    "module": "weather",
    "priority": 20,
    "regex": [
      "^como esta el clima$",
      "^cómo está el clima$",
      "^clima en (.+)$"
    ],
    "command": "weather",
    "topic_group": 1
  },
  {
    "name":"escribir_documento",
    "module":"document",
    "command":"write",
    "priority":15,

    "regex":[
        "^escribe en ([a-zA-Z0-9_-]+) (.+)$",
        "^agrega al documento ([a-zA-Z0-9_-]+) (.+)$"
    ],

    "topic_group":1,
    "content_group":2
},
{
    "name":"leer_documento",
    "module":"document",
    "command":"read",
    "priority":15,

    "regex":[
        "^lee (.+)$",
        "^abre documento (.+)$"
    ],

    "topic_group":1
},
{
    "name":"eliminar_documento",
    "module":"document",
    "command":"delete",
    "priority":15,

    "regex":[
        "^elimina (.+)$",
        "^borra (.+)$",
        "^elimina documento (.+)$",
        "^borrar documento (.+)$"
    ],

    "topic_group":1
},
{
  "name": "renombrar_documento",
  "module": "document",
  "priority": 15,
  "regex": [
    "^renombra (.+) a (.+)$",
    "^cambia el nombre de (.+) a (.+)$"
  ],
  "command": "rename",
  "old_name_group": 1,
  "new_name_group": 2
},
{
    "name": "copiar_documento",
    "module": "document",
    "priority": 15,
    "regex": [
        "^copia (.+) a (.+)$",
        "^duplica (.+) a (.+)$"
    ],
    "command": "copy",
    "old_name_group": 1,
    "new_name_group": 2
},
{
    "name": "listar_documentos",
    "module": "document",
    "priority": 20,
    "regex": [
        "^lista documentos$",
        "^listar documentos$",
        "^muestrame mis documentos$",
        "^que documentos tengo$"
    ],
    "command": "list"
},
{
    "name": "informacion_documento",
    "module": "document",
    "priority": 20,
    "regex": [
        "^informacion de (.+)$",
        "^info de (.+)$",
        "^datos de (.+)$"
    ],
    "command": "info",
    "topic_group": 1
},
{
    "name": "conversacion",
    "module": "conversation",
    "priority": 100,
    "regex": [
        "^hola$",
        "^buenos dias$",
        "^buenas tardes$",
        "^buenas noches$",
        "^gracias$",
        "^adios$",
        "^quien eres$",
        "^como estas$"
    ],
    "command": "talk",
    "topic_group": 0
}
]
